{
    "id": "shinkai-tool-json-to-md",
    "name": "Shinkai: json-to-md",
    "description": "Converts JSON to Markdown using a Nunjucks (Jinja2-like) template",
    "author": "Shinkai",
    "keywords": [
      "json-to-md",
      "shinkai",
      "nunjucks",
      "jinja2",
      "templating"
    ],
    "configurations": {
      "type": "object",
      "properties": {
        "only_system": {
          "type": "boolean"
        }
      },
      "required": [
        "only_system"
      ]
    },
    "parameters": {
      "type": "object",
      "properties": {
        "message": {
          "type": "string"
        },
        "template": {
          "type": "string"
        }
      },
      "required": [
        "message",
        "template"
      ]
    },
    "result": {
      "type": "object",
      "properties": {
        "message": {
          "type": "string"
        }
      },
      "required": [
        "message"
      ]
    }
  }